{
  "type": "FeatureCollection",
  "features": [
    {
      "type": "Feature",
      "properties": {},
      "geometry": {
        "type": "Polygon",
        "coordinates": [
          [
            [
              11.030273437499998,
              57.98480801923985
            ],
            [
              9.7119140625,
              58.309488840677645
            ],
            [
              5.537109374999999,
              57.040729838360875
            ],
            [
              5.756835937499999,
              54.49556752187406
            ],
            [
              8.876953125,
              52.77618568896171
            ],
            [
              12.480468749999998,
              53.54030739150022
            ],
            [
              12.601318359374998,
              54.73730756865752
            ],
            [
              12.843017578124998,
              55.79510545223691
            ],
            [
              11.030273437499998,
              57.98480801923985
            ]
          ]
        ]
      }
    },
    {
      "type": "Feature",
      "properties": {
        "stroke": "#555555",
        "stroke-width": 2,
        "stroke-opacity": 1,
        "fill": "#555555",
        "fill-opacity": 0.5
      },
      "geometry": {
        "type": "Polygon",
        "coordinates": [
          [
            [
              -56.25,
              84.30218294503882
            ],
            [
              -85.078125,
              83.9050579559856
            ],
            [
              -143.7890625,
              74.77584300649235
            ],
            [
              -53.78906249999999,
              55.3791104480105
            ],
            [
              -11.6015625,
              61.270232790000634
            ],
            [
              3.515625,
              56.9449741808516
            ],
            [
              0.3515625,
              76.9999351181161
            ],
            [
              -1.0546875,
              83.46037681466397
            ],
            [
              -36.5625,
              84.4740645845916
            ],
            [
              -56.25,
              84.30218294503882
            ]
          ]
        ]
      }
    }
  ]
}