{
  "ab": {
    "code": "ab",
    "color": "#e630e8",
    "name": "Abkhazian"
  },
  "aa": {
    "code": "aa",
    "color": "#9b65b4",
    "name": "Afar"
  },
  "af": {
    "code": "af",
    "color": "#e8ae30",
    "name": "Afrikaans"
  },
  "ak": {
    "code": "ak",
    "color": "#7db464",
    "name": "Akan"
  },
  "sq": {
    "code": "sq",
    "color": "#d976ef",
    "name": "Albanian"
  },
  "am": {
    "code": "am",
    "color": "#30a1e8",
    "name": "Amharic"
  },
  "ar": {
    "code": "ar",
    "color": "#7330e8",
    "name": "Arabic"
  },
  "hy": {
    "code": "hy",
    "color": "#6d428a",
    "name": "Armenian"
  },
  "as": {
    "code": "as",
    "color": "#6c64b5",
    "name": "Assamese"
  },
  "ay": {
    "code": "ay",
    "color": "#b931e8",
    "name": "Aymara"
  },
  "az": {
    "code": "az",
    "color": "#8a4251",
    "name": "Azerbaijani"
  },
  "ba": {
    "code": "ba",
    "color": "#b4a064",
    "name": "Bashkir"
  },
  "eu": {
    "code": "eu",
    "color": "#307fe8",
    "name": "Basque"
  },
  "be": {
    "code": "be",
    "color": "#33e930",
    "name": "Belarusian"
  },
  "bn": {
    "code": "bn",
    "color": "#b064b5",
    "name": "Bengali"
  },
  "bh": {
    "code": "bh",
    "color": "#5131e8",
    "name": "Bihari"
  },
  "bi": {
    "code": "bi",
    "color": "#a565b4",
    "name": "Bislama"
  },
  "bs": {
    "code": "bs",
    "color": "#cdc498",
    "name": "Bosnian"
  },
  "br": {
    "code": "br",
    "color": "#b71520",
    "name": "Breton"
  },
  "bg": {
    "code": "bg",
    "color": "#648eb4",
    "name": "Bulgarian"
  },
  "my": {
    "code": "my",
    "color": "#f0c575",
    "name": "Burmese"
  },
  "ca": {
    "code": "ca",
    "color": "#e8c631",
    "name": "Catalan"
  },
  "ceb": {
    "code": "ceb",
    "color": "#75f0a6",
    "name": "Cebuano"
  },
  "chr": {
    "code": "chr",
    "color": "#98accd",
    "name": "Cherokee"
  },
  "co": {
    "code": "co",
    "color": "#9b75f0",
    "name": "Corsican"
  },
  "hr": {
    "code": "hr",
    "color": "#437f89",
    "name": "Croatian"
  },
  "cs": {
    "code": "cs",
    "color": "#64b5a3",
    "name": "Czech"
  },
  "zh": {
    "code": "zh",
    "color": "#c998cd",
    "name": "Chinese"
  },
  "zh-Hant": {
    "code": "zh-Hant",
    "color": "#8a7242",
    "name": "Traditional Chinese"
  },
  "da": {
    "code": "da",
    "color": "#b57864",
    "name": "Danish"
  },
  "dv": {
    "code": "dv",
    "color": "#cda198",
    "name": "Dhivehi"
  },
  "nl": {
    "code": "nl",
    "color": "#b4ab64",
    "name": "Dutch"
  },
  "dz": {
    "code": "dz",
    "color": "#8a8642",
    "name": "Dzongkha"
  },
  "en": {
    "code": "en",
    "color": "#31e897",
    "name": "English"
  },
  "eo": {
    "code": "eo",
    "color": "hsl(200, 0%, 70%)",
    "name": "Esperanto"
  },
  "et": {
    "code": "et",
    "color": "#42558a",
    "name": "Estonian"
  },
  "fo": {
    "code": "fo",
    "color": "#8a5942",
    "name": "Faroese"
  },
  "fj": {
    "code": "fj",
    "color": "#83428a",
    "name": "Fijian"
  },
  "fi": {
    "code": "fi",
    "color": "#abb464",
    "name": "Finnish"
  },
  "fr": {
    "code": "fr",
    "color": "#cc31e8",
    "name": "French"
  },
  "fy": {
    "code": "fy",
    "color": "#def075",
    "name": "Frisian"
  },
  "gl": {
    "code": "gl",
    "color": "#7a64b5",
    "name": "Galician"
  },
  "lg": {
    "code": "lg",
    "color": "#a214b8",
    "name": "Ganda"
  },
  "ka": {
    "code": "ka",
    "color": "#cdbd98",
    "name": "Georgian"
  },
  "de": {
    "code": "de",
    "color": "#ab64b4",
    "name": "German"
  },
  "el": {
    "code": "el",
    "color": "#15b788",
    "name": "Greek"
  },
  "kl": {
    "code": "kl",
    "color": "#4c428a",
    "name": "Greenlandic"
  },
  "gn": {
    "code": "gn",
    "color": "#b397ce",
    "name": "Guarani"
  },
  "gu": {
    "code": "gu",
    "color": "#304ce8",
    "name": "Gujarati"
  },
  "ht": {
    "code": "ht",
    "color": "#1426b8",
    "name": "Haitian Creole"
  },
  "ha": {
    "code": "ha",
    "color": "#8de830",
    "name": "Hausa"
  },
  "haw": {
    "code": "haw",
    "color": "#f0b275",
    "name": "Hawaiian"
  },
  "iw": {
    "code": "iw",
    "color": "#9998cd",
    "name": "Hebrew"
  },
  "hi": {
    "code": "hi",
    "color": "#bee831",
    "name": "Hindi"
  },
  "hmn": {
    "code": "hmn",
    "color": "#85b814",
    "name": "Hmong"
  },
  "hu": {
    "code": "hu",
    "color": "#315ee8",
    "name": "Hungarian"
  },
  "is": {
    "code": "is",
    "color": "#afcd98",
    "name": "Icelandic"
  },
  "ig": {
    "code": "ig",
    "color": "#3131e8",
    "name": "Igbo"
  },
  "id": {
    "code": "id",
    "color": "#b314b8",
    "name": "Indonesian"
  },
  "ia": {
    "code": "ia",
    "color": "hsl(200, 0%, 70%)",
    "name": "Interlingua"
  },
  "ie": {
    "code": "ie",
    "color": "hsl(200, 0%, 70%)",
    "name": "Interlingue"
  },
  "iu": {
    "code": "iu",
    "color": "#75c9f0",
    "name": "Inuktitut"
  },
  "ik": {
    "code": "ik",
    "color": "#b87714",
    "name": "Inupiak"
  },
  "ga": {
    "code": "ga",
    "color": "#98cdcd",
    "name": "Irish"
  },
  "it": {
    "code": "it",
    "color": "#e84731",
    "name": "Italian"
  },
  "jw": {
    "code": "jw",
    "color": "#cd98cd",
    "name": "Javanese"
  },
  "ja": {
    "code": "ja",
    "color": "#cc76ef",
    "name": "Japanese"
  },
  "kn": {
    "code": "kn",
    "color": "#e89530",
    "name": "Kannada"
  },
  "ks": {
    "code": "ks",
    "color": "#897a43",
    "name": "Kashmiri"
  },
  "kk": {
    "code": "kk",
    "color": "#156db7",
    "name": "Kazakh"
  },
  "kha": {
    "code": "kha",
    "color": "#4b8a42",
    "name": "Khasi"
  },
  "km": {
    "code": "km",
    "color": "#9414b8",
    "name": "Khmer"
  },
  "rw": {
    "code": "rw",
    "color": "#acb814",
    "name": "Kinyarwanda"
  },
  "ku": {
    "code": "ku",
    "color": "#428a65",
    "name": "Kurdish"
  },
  "ky": {
    "code": "ky",
    "color": "#1550b7",
    "name": "Kyrgyz"
  },
  "ko": {
    "code": "ko",
    "color": "#cd989e",
    "name": "Korean"
  },
  "lo": {
    "code": "lo",
    "color": "#428a82",
    "name": "Laothian"
  },
  "la": {
    "code": "la",
    "color": "hsl(200, 0%, 70%)",
    "name": "Latin"
  },
  "lv": {
    "code": "lv",
    "color": "#64428a",
    "name": "Latvian"
  },
  "lif": {
    "code": "lif",
    "color": "#b83614",
    "name": "Limbu"
  },
  "ln": {
    "code": "ln",
    "color": "#ccce97",
    "name": "Lingala"
  },
  "lt": {
    "code": "lt",
    "color": "#1439b8",
    "name": "Lithuanian"
  },
  "lb": {
    "code": "lb",
    "color": "#5b428a",
    "name": "Luxembourgish"
  },
  "mk": {
    "code": "mk",
    "color": "#98c2cd",
    "name": "Macedonian"
  },
  "mg": {
    "code": "mg",
    "color": "#b75b15",
    "name": "Malagasy"
  },
  "ms": {
    "code": "ms",
    "color": "#ba97ce",
    "name": "Malay"
  },
  "ml": {
    "code": "ml",
    "color": "#98b464",
    "name": "Malayalam"
  },
  "mt": {
    "code": "mt",
    "color": "#ee75f0",
    "name": "Maltese"
  },
  "gv": {
    "code": "gv",
    "color": "#e975f0",
    "name": "Manx"
  },
  "mi": {
    "code": "mi",
    "color": "#becd98",
    "name": "Maori"
  },
  "mr": {
    "code": "mr",
    "color": "#e030e8",
    "name": "Marathi"
  },
  "mfe": {
    "code": "mfe",
    "color": "#ac14b8",
    "name": "Mauritian Creole"
  },
  "mn": {
    "code": "mn",
    "color": "#767bef",
    "name": "Mongolian"
  },
  "na": {
    "code": "na",
    "color": "#52b814",
    "name": "Nauru"
  },
  "nr": {
    "code": "nr",
    "color": "#8475f0",
    "name": "Ndebele"
  },
  "ne": {
    "code": "ne",
    "color": "#98b7cd",
    "name": "Nepali"
  },
  "no": {
    "code": "no",
    "color": "#6474b5",
    "name": "Norwegian Bokmål"
  },
  "nn": {
    "code": "nn",
    "color": "#8d30e8",
    "name": "Norwegian Nynorsk"
  },
  "ny": {
    "code": "ny",
    "color": "#e8314d",
    "name": "Nyanja"
  },
  "oc": {
    "code": "oc",
    "color": "#f0d375",
    "name": "Occitan"
  },
  "or": {
    "code": "or",
    "color": "#a330e8",
    "name": "Oriya"
  },
  "om": {
    "code": "om",
    "color": "#15b735",
    "name": "Oromo"
  },
  "ps": {
    "code": "ps",
    "color": "#759bf0",
    "name": "Pashto"
  },
  "nso": {
    "code": "nso",
    "color": "#c098cd",
    "name": "Pedi"
  },
  "fa": {
    "code": "fa",
    "color": "#5814b8",
    "name": "Persian"
  },
  "pl": {
    "code": "pl",
    "color": "#e8e730",
    "name": "Polish"
  },
  "pt": {
    "code": "pt",
    "color": "#b56466",
    "name": "Portuguese"
  },
  "pa": {
    "code": "pa",
    "color": "#b264b4",
    "name": "Punjabi"
  },
  "qu": {
    "code": "qu",
    "color": "#ac97ce",
    "name": "Quechua"
  },
  "rm": {
    "code": "rm",
    "color": "#e376ef",
    "name": "Rhaeto-Romance"
  },
  "ro": {
    "code": "ro",
    "color": "#8764b5",
    "name": "Romanian"
  },
  "rn": {
    "code": "rn",
    "color": "#f09975",
    "name": "Rundi"
  },
  "ru": {
    "code": "ru",
    "color": "#e87330",
    "name": "Russian"
  },
  "sm": {
    "code": "sm",
    "color": "#6a8a42",
    "name": "Samoan"
  },
  "sg": {
    "code": "sg",
    "color": "#989ecd",
    "name": "Sango"
  },
  "sa": {
    "code": "sa",
    "color": "#b49664",
    "name": "Sanskrit"
  },
  "sco": {
    "code": "sco",
    "color": "#14b3b8",
    "name": "Scots"
  },
  "gd": {
    "code": "gd",
    "color": "#768bef",
    "name": "Scottish Gaelic"
  },
  "sr": {
    "code": "sr",
    "color": "#f07875",
    "name": "Serbian"
  },
  "crs": {
    "code": "crs",
    "color": "#c698cd",
    "name": "Seselwa"
  },
  "st": {
    "code": "st",
    "color": "#98cdba",
    "name": "Sesotho"
  },
  "sn": {
    "code": "sn",
    "color": "#42718a",
    "name": "Shona"
  },
  "sd": {
    "code": "sd",
    "color": "#64aeb5",
    "name": "Sindhi"
  },
  "si": {
    "code": "si",
    "color": "#be76ef",
    "name": "Sinhalese"
  },
  "ss": {
    "code": "ss",
    "color": "#b8a114",
    "name": "Siswant"
  },
  "sk": {
    "code": "sk",
    "color": "#cb98cd",
    "name": "Slovak"
  },
  "sl": {
    "code": "sl",
    "color": "#cdb798",
    "name": "Slovenian"
  },
  "so": {
    "code": "so",
    "color": "#a398cd",
    "name": "Somali"
  },
  "es": {
    "code": "es",
    "color": "#64b47c",
    "name": "Spanish"
  },
  "su": {
    "code": "su",
    "color": "#98a4cd",
    "name": "Sundanese"
  },
  "sw": {
    "code": "sw",
    "color": "#6d14b8",
    "name": "Swahili"
  },
  "sv": {
    "code": "sv",
    "color": "#30e8df",
    "name": "Swedish"
  },
  "syr": {
    "code": "syr",
    "color": "#87428a",
    "name": "Syriac"
  },
  "tl": {
    "code": "tl",
    "color": "#7e4389",
    "name": "Tagalog"
  },
  "tg": {
    "code": "tg",
    "color": "#8a6842",
    "name": "Tajik"
  },
  "ta": {
    "code": "ta",
    "color": "#30c8e8",
    "name": "Tamil"
  },
  "tt": {
    "code": "tt",
    "color": "#8014b8",
    "name": "Tatar"
  },
  "te": {
    "code": "te",
    "color": "#646bb5",
    "name": "Telugu"
  },
  "th": {
    "code": "th",
    "color": "#bff075",
    "name": "Thai"
  },
  "bo": {
    "code": "bo",
    "color": "#b58964",
    "name": "Tibetan"
  },
  "ti": {
    "code": "ti",
    "color": "#148fb8",
    "name": "Tigrinya"
  },
  "to": {
    "code": "to",
    "color": "#efe776",
    "name": "Tonga"
  },
  "ts": {
    "code": "ts",
    "color": "#434e89",
    "name": "Tsonga"
  },
  "tn": {
    "code": "tn",
    "color": "#8a4742",
    "name": "Tswana"
  },
  "tr": {
    "code": "tr",
    "color": "#75f0dc",
    "name": "Turkish"
  },
  "tk": {
    "code": "tk",
    "color": "#1f14b8",
    "name": "Turkmen"
  },
  "ug": {
    "code": "ug",
    "color": "#b814b7",
    "name": "Uighur"
  },
  "uk": {
    "code": "uk",
    "color": "#d730e8",
    "name": "Ukrainian"
  },
  "ur": {
    "code": "ur",
    "color": "#b88a14",
    "name": "Urdu"
  },
  "uz": {
    "code": "uz",
    "color": "#98cd9d",
    "name": "Uzbek"
  },
  "ve": {
    "code": "ve",
    "color": "#42638a",
    "name": "Venda"
  },
  "vi": {
    "code": "vi",
    "color": "#ac76ef",
    "name": "Vietnamese"
  },
  "vo": {
    "code": "vo",
    "color": "#89428a",
    "name": "Volapuk"
  },
  "war": {
    "code": "war",
    "color": "#7c8a42",
    "name": "Waray"
  },
  "cy": {
    "code": "cy",
    "color": "#647eb4",
    "name": "Welsh"
  },
  "wo": {
    "code": "wo",
    "color": "#75e3f0",
    "name": "Wolof"
  },
  "xh": {
    "code": "xh",
    "color": "#42448a",
    "name": "Xhosa"
  },
  "xx-Bugi": {
    "code": "xx-Bugi",
    "color": "#76428a",
    "name": "X_buginese"
  },
  "xx-Goth": {
    "code": "xx-Goth",
    "color": "#cdad98",
    "name": "X_gothic"
  },
  "tlh": {
    "code": "tlh",
    "color": "hsl(200, 0%, 70%)",
    "name": "X_klingon"
  },
  "zzp": {
    "code": "zzp",
    "color": "hsl(200, 0%, 70%)",
    "name": "X_pig_latin"
  },
  "yi": {
    "code": "yi",
    "color": "#91f075",
    "name": "Yiddish"
  },
  "yo": {
    "code": "yo",
    "color": "#649eb5",
    "name": "Yoruba"
  },
  "za": {
    "code": "za",
    "color": "#3c15b7",
    "name": "Zhuang"
  },
  "zu": {
    "code": "zu",
    "color": "#75b1f0",
    "name": "Zulu"
  }
}
